{
    "success": true,
    "batch_data": {
        "batch_id": "1361c4b1-d578-4581-b2d4-f218902f4b17",
        "entries": {
            "d5d84154-0b5a-47a3-ab58-e6c0d87fc69e": {
                "id": "f00b18e3-28d5-47ea-a8e7-29d3c3a913ab",
                "batch_id": "1361c4b1-d578-4581-b2d4-f218902f4b17",
                "machine_id": "d5d84154-0b5a-47a3-ab58-e6c0d87fc69e",
                "machine_name": "Atomstack M4",
                "url": "https://www.ikier.com/collections/m4-pro-infrared-laser/products/atomstack-m4-fiber-laser-marking-machine",
                "success": true,
                "old_price": 1279,
                "new_price": 1279.0,
                "price_change": null,
                "percentage_change": null,
                "error": null,
                "start_time": "2025-07-09T18:18:03.447404+00:00",
                "end_time": "2025-07-09T18:18:03.447404+00:00",
                "duration_seconds": null,
                "extraction_method": "Meta tag (og:price:amount)",
                "http_status": null,
                "html_size": null,
                "extraction_attempts": null,
                "variant_attribute": null,
                "tier": null,
                "extracted_confidence": null,
                "validation_confidence": null,
                "needs_review": false,
                "review_reason": null,
                "confidence": null
            },
            "69c389c5-5e86-4299-935b-4ed0296abe59": {
                "id": "93495d6a-a900-4bd3-8520-3985891d8710",
                "batch_id": "1361c4b1-d578-4581-b2d4-f218902f4b17",
                "machine_id": "69c389c5-5e86-4299-935b-4ed0296abe59",
                "machine_name": "Mr Carve S4-20W",
                "url": "https://mr-carve.com/",
                "success": false,
                "old_price": null,
                "new_price": null,
                "price_change": null,
                "percentage_change": null,
                "error": "Failed to extract price",
                "start_time": "2025-07-09T18:18:05.024306+00:00",
                "end_time": "2025-07-09T18:18:05.024306+00:00",
                "duration_seconds": null,
                "extraction_method": null,
                "http_status": null,
                "html_size": null,
                "extraction_attempts": null,
                "variant_attribute": null,
                "tier": null,
                "extracted_confidence": null,
                "validation_confidence": null,
                "needs_review": false,
                "review_reason": null,
                "confidence": null
            },
            "33c14c58-a416-4ae4-b06a-d07823ec3f4f": {
                "id": "e2f39134-e95f-4fe6-a042-274b618d17e1",
                "batch_id": "1361c4b1-d578-4581-b2d4-f218902f4b17",
                "machine_id": "33c14c58-a416-4ae4-b06a-d07823ec3f4f",
                "machine_name": "WeCreat Lumos",
                "url": "https://wecreat.com/pages/wecreat-lumos",
                "success": true,
                "old_price": 1199.99,
                "new_price": 1199.99,
                "price_change": null,
                "percentage_change": null,
                "error": null,
                "start_time": "2025-07-09T18:18:05.926748+00:00",
                "end_time": "2025-07-09T18:18:05.926748+00:00",
                "duration_seconds": null,
                "extraction_method": "Site-specific fallback (filtered:.price)",
                "http_status": null,
                "html_size": null,
                "extraction_attempts": null,
                "variant_attribute": null,
                "tier": null,
                "extracted_confidence": null,
                "validation_confidence": null,
                "needs_review": false,
                "review_reason": null,
                "confidence": null
            },
            "355edc0d-3b10-497a-9043-23ee72d9a900": {
                "id": "afa14d1c-16c8-475f-894c-7ea81531343a",
                "batch_id": "1361c4b1-d578-4581-b2d4-f218902f4b17",
                "machine_id": "355edc0d-3b10-497a-9043-23ee72d9a900",
                "machine_name": "OneLaser Hydra 13",
                "url": "https://www.1laser.com/products/onelaser-hydra-13-cabinet-dual-laser-system-with-130w-glass-tube-and-38wrf-metal-tube",
                "success": true,
                "old_price": 8995,
                "new_price": 8995.0,
                "price_change": null,
                "percentage_change": null,
                "error": null,
                "start_time": "2025-07-09T18:17:44.246391+00:00",
                "end_time": "2025-07-09T18:17:44.246391+00:00",
                "duration_seconds": null,
                "extraction_method": "Meta tag (og:price:amount)",
                "http_status": null,
                "html_size": null,
                "extraction_attempts": null,
                "variant_attribute": null,
                "tier": null,
                "extracted_confidence": null,
                "validation_confidence": null,
                "needs_review": false,
                "review_reason": null,
                "confidence": null
            },
            "a4c0fd86-5122-41a8-ae4c-b4db6cb4e92a": {
                "id": "9e4b6dc9-18e4-4163-b05b-60e34729085d",
                "batch_id": "1361c4b1-d578-4581-b2d4-f218902f4b17",
                "machine_id": "a4c0fd86-5122-41a8-ae4c-b4db6cb4e92a",
                "machine_name": "iKier K1 Pro Max 48W",
                "url": "https://atomstack.com/products/ikier-k1-pro-max-48w-24w-power-switching-laser-engraving-and-cutting-machine",
                "success": false,
                "old_price": null,
                "new_price": null,
                "price_change": null,
                "percentage_change": null,
                "error": "URL not found (404): https://atomstack.com/products/ikier-k1-pro-max-48w-24w-power-switching-laser-engraving-and-cutting-machine. Tried 2 alternatives.",
                "start_time": "2025-07-09T18:17:45.959221+00:00",
                "end_time": "2025-07-09T18:17:45.959221+00:00",
                "duration_seconds": null,
                "extraction_method": null,
                "http_status": null,
                "html_size": null,
                "extraction_attempts": null,
                "variant_attribute": null,
                "tier": null,
                "extracted_confidence": null,
                "validation_confidence": null,
                "needs_review": false,
                "review_reason": null,
                "confidence": null
            },
            "bc4031f6-2442-48eb-b06a-c40829e5ef41": {
                "id": "354003d0-34a5-4e5d-b6b2-54afe1949438",
                "batch_id": "1361c4b1-d578-4581-b2d4-f218902f4b17",
                "machine_id": "bc4031f6-2442-48eb-b06a-c40829e5ef41",
                "machine_name": "Thunder Aurora 8",
                "url": "https://www.thunderlaserusa.com/aurora-8",
                "success": false,
                "old_price": null,
                "new_price": null,
                "price_change": null,
                "percentage_change": null,
                "error": "Thunder Laser machines temporarily excluded from batch updates",
                "start_time": "2025-07-09T18:17:46.290809+00:00",
                "end_time": "2025-07-09T18:17:46.290809+00:00",
                "duration_seconds": null,
                "extraction_method": null,
                "http_status": null,
                "html_size": null,
                "extraction_attempts": null,
                "variant_attribute": null,
                "tier": null,
                "extracted_confidence": null,
                "validation_confidence": null,
                "needs_review": false,
                "review_reason": null,
                "confidence": null
            },
            "4923b2ee-8a9e-4743-9643-af7c91feb806": {
                "id": "2cdb5f82-9555-4c00-a846-a7ee07350e07",
                "batch_id": "1361c4b1-d578-4581-b2d4-f218902f4b17",
                "machine_id": "4923b2ee-8a9e-4743-9643-af7c91feb806",
                "machine_name": "Thunder Aurora 8 MOPA",
                "url": "https://www.thunderlaserusa.com/aurora-8-mopa/",
                "success": false,
                "old_price": null,
                "new_price": null,
                "price_change": null,
                "percentage_change": null,
                "error": "Thunder Laser machines temporarily excluded from batch updates",
                "start_time": "2025-07-09T18:17:46.62615+00:00",
                "end_time": "2025-07-09T18:17:46.62615+00:00",
                "duration_seconds": null,
                "extraction_method": null,
                "http_status": null,
                "html_size": null,
                "extraction_attempts": null,
                "variant_attribute": null,
                "tier": null,
                "extracted_confidence": null,
                "validation_confidence": null,
                "needs_review": false,
                "review_reason": null,
                "confidence": null
            },
            "12e84cde-ea66-414f-82d3-8a289fd3cd46": {
                "id": "2676ee14-708e-4938-8c47-ebaaa8aef848",
                "batch_id": "1361c4b1-d578-4581-b2d4-f218902f4b17",
                "machine_id": "12e84cde-ea66-414f-82d3-8a289fd3cd46",
                "machine_name": "Thunder Aurora Lite",
                "url": "https://www.thunderlaserusa.com/aurora-lite/",
                "success": false,
                "old_price": null,
                "new_price": null,
                "price_change": null,
                "percentage_change": null,
                "error": "Thunder Laser machines temporarily excluded from batch updates",
                "start_time": "2025-07-09T18:17:46.944711+00:00",
                "end_time": "2025-07-09T18:17:46.944711+00:00",
                "duration_seconds": null,
                "extraction_method": null,
                "http_status": null,
                "html_size": null,
                "extraction_attempts": null,
                "variant_attribute": null,
                "tier": null,
                "extracted_confidence": null,
                "validation_confidence": null,
                "needs_review": false,
                "review_reason": null,
                "confidence": null
            },
            "9e3f3869-c7bf-468f-b981-92efaf91da79": {
                "id": "c22d9823-fb73-4289-aa44-de872a1d8cf2",
                "batch_id": "1361c4b1-d578-4581-b2d4-f218902f4b17",
                "machine_id": "9e3f3869-c7bf-468f-b981-92efaf91da79",
                "machine_name": "Thunder Bolt",
                "url": "https://www.thunderlaserusa.com/bolt/",
                "success": false,
                "old_price": null,
                "new_price": null,
                "price_change": null,
                "percentage_change": null,
                "error": "Thunder Laser machines temporarily excluded from batch updates",
                "start_time": "2025-07-09T18:17:47.259204+00:00",
                "end_time": "2025-07-09T18:17:47.259204+00:00",
                "duration_seconds": null,
                "extraction_method": null,
                "http_status": null,
                "html_size": null,
                "extraction_attempts": null,
                "variant_attribute": null,
                "tier": null,
                "extracted_confidence": null,
                "validation_confidence": null,
                "needs_review": false,
                "review_reason": null,
                "confidence": null
            },
            "a6abf51b-351c-4a1e-ac4c-62d83fbe0051": {
                "id": "90674c20-8114-4dcc-9633-83bdf8b1c534",
                "batch_id": "1361c4b1-d578-4581-b2d4-f218902f4b17",
                "machine_id": "a6abf51b-351c-4a1e-ac4c-62d83fbe0051",
                "machine_name": "Thunder Bolt Pro 22",
                "url": "https://www.thunderlaserusa.com/bolt-pro-22/",
                "success": false,
                "old_price": null,
                "new_price": null,
                "price_change": null,
                "percentage_change": null,
                "error": "Thunder Laser machines temporarily excluded from batch updates",
                "start_time": "2025-07-09T18:17:47.549939+00:00",
                "end_time": "2025-07-09T18:17:47.549939+00:00",
                "duration_seconds": null,
                "extraction_method": null,
                "http_status": null,
                "html_size": null,
                "extraction_attempts": null,
                "variant_attribute": null,
                "tier": null,
                "extracted_confidence": null,
                "validation_confidence": null,
                "needs_review": false,
                "review_reason": null,
                "confidence": null
            },
            "fe10192a-c6f1-4263-ad74-16c87d67d5f3": {
                "id": "a6c37655-ea4c-4d23-b2d8-8e01e0464dda",
                "batch_id": "1361c4b1-d578-4581-b2d4-f218902f4b17",
                "machine_id": "fe10192a-c6f1-4263-ad74-16c87d67d5f3",
                "machine_name": "Thunder Laser Plus 51",
                "url": "https://www.thunderlaserusa.com/nova-plus-51/",
                "success": false,
                "old_price": null,
                "new_price": null,
                "price_change": null,
                "percentage_change": null,
                "error": "Thunder Laser machines temporarily excluded from batch updates",
                "start_time": "2025-07-09T18:17:47.873804+00:00",
                "end_time": "2025-07-09T18:17:47.873804+00:00",
                "duration_seconds": null,
                "extraction_method": null,
                "http_status": null,
                "html_size": null,
                "extraction_attempts": null,
                "variant_attribute": null,
                "tier": null,
                "extracted_confidence": null,
                "validation_confidence": null,
                "needs_review": false,
                "review_reason": null,
                "confidence": null
            },
            "81a38d6c-1813-4d4a-8396-29ee36d5918e": {
                "id": "aa26e3a8-ad8a-4613-b6f7-e10bb5f073b2",
                "batch_id": "1361c4b1-d578-4581-b2d4-f218902f4b17",
                "machine_id": "81a38d6c-1813-4d4a-8396-29ee36d5918e",
                "machine_name": "Thunder Nova 24",
                "url": "https://www.thunderlaserusa.com/nova-24/",
                "success": false,
                "old_price": null,
                "new_price": null,
                "price_change": null,
                "percentage_change": null,
                "error": "Thunder Laser machines temporarily excluded from batch updates",
                "start_time": "2025-07-09T18:17:48.154502+00:00",
                "end_time": "2025-07-09T18:17:48.154502+00:00",
                "duration_seconds": null,
                "extraction_method": null,
                "http_status": null,
                "html_size": null,
                "extraction_attempts": null,
                "variant_attribute": null,
                "tier": null,
                "extracted_confidence": null,
                "validation_confidence": null,
                "needs_review": false,
                "review_reason": null,
                "confidence": null
            },
            "045f6d76-a4fa-46cd-aa20-e049dda512f6": {
                "id": "bbe9df30-92ee-40c5-bf60-57d159303f37",
                "batch_id": "1361c4b1-d578-4581-b2d4-f218902f4b17",
                "machine_id": "045f6d76-a4fa-46cd-aa20-e049dda512f6",
                "machine_name": "Thunder Nova 35",
                "url": "https://www.thunderlaserusa.com/nova-35/",
                "success": false,
                "old_price": null,
                "new_price": null,
                "price_change": null,
                "percentage_change": null,
                "error": "Thunder Laser machines temporarily excluded from batch updates",
                "start_time": "2025-07-09T18:17:48.444155+00:00",
                "end_time": "2025-07-09T18:17:48.444155+00:00",
                "duration_seconds": null,
                "extraction_method": null,
                "http_status": null,
                "html_size": null,
                "extraction_attempts": null,
                "variant_attribute": null,
                "tier": null,
                "extracted_confidence": null,
                "validation_confidence": null,
                "needs_review": false,
                "review_reason": null,
                "confidence": null
            },
            "0993bbcb-b705-4593-9565-4967121d1d79": {
                "id": "c302eccf-04ff-4a2a-864d-a62bf31b2651",
                "batch_id": "1361c4b1-d578-4581-b2d4-f218902f4b17",
                "machine_id": "0993bbcb-b705-4593-9565-4967121d1d79",
                "machine_name": "Thunder Nova 51",
                "url": "https://www.thunderlaserusa.com/nova-51/",
                "success": false,
                "old_price": null,
                "new_price": null,
                "price_change": null,
                "percentage_change": null,
                "error": "Thunder Laser machines temporarily excluded from batch updates",
                "start_time": "2025-07-09T18:17:48.713794+00:00",
                "end_time": "2025-07-09T18:17:48.713794+00:00",
                "duration_seconds": null,
                "extraction_method": null,
                "http_status": null,
                "html_size": null,
                "extraction_attempts": null,
                "variant_attribute": null,
                "tier": null,
                "extracted_confidence": null,
                "validation_confidence": null,
                "needs_review": false,
                "review_reason": null,
                "confidence": null
            },
            "b6975eb0-1cc5-4ce6-8157-6f2e55e6db2f": {
                "id": "4f054f75-6d2b-459a-a4e1-0d062eafbc78",
                "batch_id": "1361c4b1-d578-4581-b2d4-f218902f4b17",
                "machine_id": "b6975eb0-1cc5-4ce6-8157-6f2e55e6db2f",
                "machine_name": "Thunder Nova 63",
                "url": "https://www.thunderlaserusa.com/nova-63/",
                "success": false,
                "old_price": null,
                "new_price": null,
                "price_change": null,
                "percentage_change": null,
                "error": "Thunder Laser machines temporarily excluded from batch updates",
                "start_time": "2025-07-09T18:17:48.980107+00:00",
                "end_time": "2025-07-09T18:17:48.980107+00:00",
                "duration_seconds": null,
                "extraction_method": null,
                "http_status": null,
                "html_size": null,
                "extraction_attempts": null,
                "variant_attribute": null,
                "tier": null,
                "extracted_confidence": null,
                "validation_confidence": null,
                "needs_review": false,
                "review_reason": null,
                "confidence": null
            },
            "9ba448a6-9027-4851-84b7-c69890de5b4b": {
                "id": "70facbd3-b339-412b-9083-1eaf4dce7c02",
                "batch_id": "1361c4b1-d578-4581-b2d4-f218902f4b17",
                "machine_id": "9ba448a6-9027-4851-84b7-c69890de5b4b",
                "machine_name": "Thunder Nova Plus 24",
                "url": "https://www.thunderlaserusa.com/nova-plus-24/",
                "success": false,
                "old_price": null,
                "new_price": null,
                "price_change": null,
                "percentage_change": null,
                "error": "Thunder Laser machines temporarily excluded from batch updates",
                "start_time": "2025-07-09T18:17:49.244881+00:00",
                "end_time": "2025-07-09T18:17:49.244881+00:00",
                "duration_seconds": null,
                "extraction_method": null,
                "http_status": null,
                "html_size": null,
                "extraction_attempts": null,
                "variant_attribute": null,
                "tier": null,
                "extracted_confidence": null,
                "validation_confidence": null,
                "needs_review": false,
                "review_reason": null,
                "confidence": null
            },
            "4860c090-f592-45c3-a557-39a741325f4f": {
                "id": "f96b7c72-acd0-41e6-b1cd-d1721edf7af6",
                "batch_id": "1361c4b1-d578-4581-b2d4-f218902f4b17",
                "machine_id": "4860c090-f592-45c3-a557-39a741325f4f",
                "machine_name": "Thunder Nova Plus 35",
                "url": "https://www.thunderlaserusa.com/nova-plus-35/",
                "success": false,
                "old_price": null,
                "new_price": null,
                "price_change": null,
                "percentage_change": null,
                "error": "Thunder Laser machines temporarily excluded from batch updates",
                "start_time": "2025-07-09T18:17:49.507162+00:00",
                "end_time": "2025-07-09T18:17:49.507162+00:00",
                "duration_seconds": null,
                "extraction_method": null,
                "http_status": null,
                "html_size": null,
                "extraction_attempts": null,
                "variant_attribute": null,
                "tier": null,
                "extracted_confidence": null,
                "validation_confidence": null,
                "needs_review": false,
                "review_reason": null,
                "confidence": null
            },
            "2503760f-cff8-435f-9cf4-9b7094d055c8": {
                "id": "69f68f48-a740-4f35-b10d-6a9fcd564b26",
                "batch_id": "1361c4b1-d578-4581-b2d4-f218902f4b17",
                "machine_id": "2503760f-cff8-435f-9cf4-9b7094d055c8",
                "machine_name": "Atomstack M4 Pro",
                "url": "https://www.ikier.com/collections/m4-pro-infrared-laser/products/atomstack-m4-pro-portable-dual-laser-engraver",
                "success": true,
                "old_price": 1599,
                "new_price": 1599.0,
                "price_change": null,
                "percentage_change": null,
                "error": null,
                "start_time": "2025-07-09T18:17:50.363562+00:00",
                "end_time": "2025-07-09T18:17:50.363562+00:00",
                "duration_seconds": null,
                "extraction_method": "Meta tag (og:price:amount)",
                "http_status": null,
                "html_size": null,
                "extraction_attempts": null,
                "variant_attribute": null,
                "tier": null,
                "extracted_confidence": null,
                "validation_confidence": null,
                "needs_review": false,
                "review_reason": null,
                "confidence": null
            },
            "011044ee-ab5e-448d-9787-d58948dec748": {
                "id": "679809cc-404d-4943-95ad-cae9d347aa4c",
                "batch_id": "1361c4b1-d578-4581-b2d4-f218902f4b17",
                "machine_id": "011044ee-ab5e-448d-9787-d58948dec748",
                "machine_name": "Rendyr Optic",
                "url": "https://rendyr.com/products/optic-the-portable-laser-cutter",
                "success": false,
                "old_price": null,
                "new_price": null,
                "price_change": null,
                "percentage_change": null,
                "error": "Failed to fetch product page after retries",
                "start_time": "2025-07-09T18:18:01.609736+00:00",
                "end_time": "2025-07-09T18:18:01.609736+00:00",
                "duration_seconds": null,
                "extraction_method": null,
                "http_status": null,
                "html_size": null,
                "extraction_attempts": null,
                "variant_attribute": null,
                "tier": null,
                "extracted_confidence": null,
                "validation_confidence": null,
                "needs_review": false,
                "review_reason": null,
                "confidence": null
            },
            "62961076-62c0-40c6-a57b-78010a186945": {
                "id": "00861d20-f404-4c20-845b-86d177c6db01",
                "batch_id": "1361c4b1-d578-4581-b2d4-f218902f4b17",
                "machine_id": "62961076-62c0-40c6-a57b-78010a186945",
                "machine_name": "iKier K1 Pro Max 70W",
                "url": "https://atomstack.com/products/ikier-k1-pro-max-70w-power-switching-diode-laser-cutter",
                "success": false,
                "old_price": null,
                "new_price": null,
                "price_change": null,
                "percentage_change": null,
                "error": "URL not found (404): https://atomstack.com/products/ikier-k1-pro-max-70w-power-switching-diode-laser-cutter. Tried 2 alternatives.",
                "start_time": "2025-07-09T18:18:02.570519+00:00",
                "end_time": "2025-07-09T18:18:02.570519+00:00",
                "duration_seconds": null,
                "extraction_method": null,
                "http_status": null,
                "html_size": null,
                "extraction_attempts": null,
                "variant_attribute": null,
                "tier": null,
                "extracted_confidence": null,
                "validation_confidence": null,
                "needs_review": false,
                "review_reason": null,
                "confidence": null
            },
            "d9fb020a-1ec2-4661-98e3-aa51f6882b2f": {
                "id": "1891616c-103a-4a50-9942-6ba687b97ad4",
                "batch_id": "1361c4b1-d578-4581-b2d4-f218902f4b17",
                "machine_id": "d9fb020a-1ec2-4661-98e3-aa51f6882b2f",
                "machine_name": "Thunder Bolt Plus",
                "url": "https://www.thunderlaserusa.com/bolt-plus/",
                "success": false,
                "old_price": null,
                "new_price": null,
                "price_change": null,
                "percentage_change": null,
                "error": "Thunder Laser machines temporarily excluded from batch updates",
                "start_time": "2025-07-09T18:18:02.885063+00:00",
                "end_time": "2025-07-09T18:18:02.885063+00:00",
                "duration_seconds": null,
                "extraction_method": null,
                "http_status": null,
                "html_size": null,
                "extraction_attempts": null,
                "variant_attribute": null,
                "tier": null,
                "extracted_confidence": null,
                "validation_confidence": null,
                "needs_review": false,
                "review_reason": null,
                "confidence": null
            }
        },
        "stats": {
            "batch": {
                "id": "1361c4b1-d578-4581-b2d4-f218902f4b17",
                "start_time": "2025-07-09T18:17:42.077494+00:00",
                "end_time": "2025-07-09T18:18:05.999123+00:00",
                "total_machines": 21,
                "days_threshold": 1,
                "created_by": null,
                "batch_type": "price_update",
                "status": "completed",
                "metadata": "{\"limit\": null, \"max_workers\": 5, \"machine_ids\": null}"
            },
            "success_counts": {
                "total": 21,
                "successful": 4,
                "failed": 17,
                "percent_complete": 100.0
            },
            "price_stats": {
                "updated": 0,
                "unchanged": 4,
                "increased": 0,
                "decreased": 0,
                "avg_change_pct": null,
                "max_increase_pct": null,
                "max_decrease_pct": null
            }
        },
        "timestamp": "2025-07-09T18:19:15.773873Z"
    }
}
